afori_utils/__init__.py
afori_utils/debug_utils.py
afori_utils/pyplot_utils.py
afori_utils/sync_utils.py
afori_utils-1.1.0.dist-info/LICENSE.txt
afori_utils-1.1.0.dist-info/METADATA
afori_utils-1.1.0.dist-info/WHEEL
afori_utils-1.1.0.dist-info/top_level.txt
afori_utils-1.1.0.dist-info/RECORD
