Metadata-Version: 2.1
Name: afori-utils
Version: 1.1.0
Summary: Some utils by Dor Miron
Home-page: https://github.com/dor-miron/afori_utils
Author: Dor Miron
Author-email: dor00012@gmail.com
License: LICENSE.txt
Platform: UNKNOWN
Classifier: Programming Language :: Python :: 3
Classifier: License :: OSI Approved :: GNU General Public License (GPL)
License-File: LICENSE.txt
Requires-Dist: numpy (>=1.20)
Requires-Dist: matplotlib (>=3.4)
